verilog lab7/library_input.v
`include "constants.h"


///////////////////////////////////////////////////////////////////////////////////
//~~~~~~~~~~~~~~~~~~~~~~~~~~~~~~~~~ ALU ~~~~~~~~~~~~~~~~~~~~~~~~~~~~~~~~~~~~~~~~~~//
//																				  //
// Small ALU. Inputs: inA, inB. Output: out. 									  //
// Operations: bitwise and (op = 0)												  //
//             bitwise or  (op = 1)												  //
//             addition (op = 2)												  //
//             subtraction (op = 6)												  //
//             slt  (op = 7)													  //
//             nor (op = 12)													  //
////////////////////////////////////////////////////////////////////////////////////

module ALU (out, zero, inA, inB, alu_ctrl);

  parameter N = 32;
  input [3:0] alu_ctrl;
  input [N-1:0] inA, inB;
  output reg [N-1:0] out;
  output wire zero;
  
  assign zero = (out==0);
  
  always @ (alu_ctrl, inA, inB) begin
    
    case (alu_ctrl)
      4'b0000: out <= inA&inB;
      4'b0001: out <= inA | inB;       	// or
      4'b0010: out <= inA + inB;       	// add
      4'b0110: out <= inA - inB;       	// substract
      4'b0111: out <= inA < inB ? 1:0; 	// slt
      4'b1100: out <= ~(inA | inB);		// nor
      default: out <= 1'bx;
    endcase
  end
  
endmodule

///////////////////////////////////////////////////////////////////////////////////
//~~~~~~~~~~~~~~~~~~~~~~~~~~~~~ Program Counter ~~~~~~~~~~~~~~~~~~~~~~~~~~~~~~~~//
//																				//
// 				Sets the new program counter as the current pc					//
//																				//
//////////////////////////////////////////////////////////////////////////////////

module ProgramCounter (clock, reset, PC_new, PC);

	input reset, clock;
	input [31:0] PC_new;
	output reg [31:0] PC;

	always @(posedge clock, negedge reset)
		begin
			if (reset == 1'b0)	// an to reset einai 0 krata 0 kai ton program counter
				PC <= 0;
			else
				PC <= PC_new;	// alliws dwse ston trexon pc timh ish me thn epomenh dieu8unsh
		end

endmodule

///////////////////////////////////////////////////////////////////////////////////
//~~~~~~~~~~~~~~~~~~~~~~~~~~~~~~~~ Memory ~~~~~~~~~~~~~~~~~~~~~~~~~~~~~~~~~~~~~~//
//																				//
// 		Memory (active 1024 words, from 10 address lsbs).						//
//      Read : enable ren, address addr, data dout								//
//      Write: enable wen, address addr, data din.								//
//																				//
//////////////////////////////////////////////////////////////////////////////////

module Memory (clock, reset, ren, wen, addr, din, dout);
  input         ren, wen;
  input clock, reset;
  input  [31:0] addr, din;
  output [31:0] dout;

  reg [31:0] data[4095:0];
  wire [31:0] dout;

  always @(ren or wen)
    if (ren & wen)
      $display ("\nMemory ERROR (time %0d): ren and wen both active!\n", $time);

  always @(posedge ren or posedge wen) begin
    if (addr[31:10] != 0)
      $display("Memory WARNING (time %0d): address msbs are not zero\n", $time);
  end  

  assign dout = ((reset==1'b1) && (wen==1'b0) && (ren==1'b1)) ? data[addr[9:0]] : 32'bx;
  
  always @(negedge clock , negedge reset, din, wen, ren, addr)
   begin
    if ((reset==1'b1) && (wen == 1'b1) && (ren==1'b0))
        data[addr[9:0]] = din;
   end

endmodule

///////////////////////////////////////////////////////////////////////////////////
//~~~~~~~~~~~~~~~~~~~~~~~~~~~~~~~Register File ~~~~~~~~~~~~~~~~~~~~~~~~~~~~~~~~~~//
//																				 //
// 		Read ports: address raA, data rdA										 //
//                          address raB, data rdB								 //
//      Write port: address wa, data wd, enable wen.							 //
//																				 //
///////////////////////////////////////////////////////////////////////////////////

module RegFile (clock, reset, raA, raB, wa, wen, wd, rdA, rdB);


	output wire [31:0] rdA, rdB;
	input [31:0] wd;
	input [4:0] raA, raB, wa;
	input wen, reset, clock;
	reg [31:0] data [31:0];
	integer i;


	assign rdA = data[raA];
	assign rdB = data[raB];
	// Write Section
	always @(negedge clock, negedge reset)	// the register file should be written at 
		begin								// the negative edge of the input clock

			if (reset==1'b0)
		 	begin
		  		for(i=0;i<32;i=i+1)
					data[i] <= 32'b0;		//otan to reset einai 0 mhdenizw olous ts kataxwrhtes
			end

			if ((wen==1'b1) && (reset==1'b1))	// alliws dwse ston ka8e kataxwrhth timh idia me
					data[wa] <= wd;  			// idia me ton au3oda ari8mo tu

		end


endmodule

///////////////////////////////////////////////////////////////////////////////////
//~~~~~~~~~~~~~~~~~~~~~~~~~~~~~~~~ ADDER ~~~~~~~~~~~~~~~~~~~~~~~~~~~~~~~~~~~~~~~~~//
//																				  //
// 					Adds 4 bytes to move to the next instruction				  //
//																				  //
////////////////////////////////////////////////////////////////////////////////////

module Adder (current, next_pc);

	parameter step = 4;
	input [31:0] current;
	output wire [31:0] next_pc;

	assign next_pc = current + step;
	
endmodule

///////////////////////////////////////////////////////////////////////////////////
//~~~~~~~~~~~~~~~~~~~~~~~~~~~~~~~~~~ CPU ~~~~~~~~~~~~~~~~~~~~~~~~~~~~~~~~~~~~~~~~~//
//																				  //
// 					A module that describes the function of cpu					  //
//																				  //
////////////////////////////////////////////////////////////////////////////////////
                                                                                  
module CPU (clock, reset);

	input clock, reset;
	input regWrite;
	wire [1:0] alu_op;
	wire [3:0] alu_ctrl;
	wire [5:0] op, func_code;
	
	// enwnoume to FSM me ta upoloipa stoixeia //
	Main_decoder dec_main (op, regWrite, alu_op);
	Alu_decoder dec_alu (alu_op, func_code, alu_ctrl);
	data_path datapass (clock, reset, regWrite, alu_ctrl, op, func_code);

endmodule

verilog lab7/data_path.v

module data_path (clock, reset, regWrite, alu_ctrl, op, func_code);

	input clock, reset, regWrite;
	input [3:0] alu_ctrl;
	output [5:0] op, func_code;

	wire [31:0] instr, pc_new, pc, rdA, rdB, din, out;


	// enwnoume ta stoixeia ektos tou FSM //
	ProgramCounter reloaded_pc (clock, reset, pc_new, pc);
	Adder additive (pc, pc_new);
	Memory mem (clock, reset, 1, 0, pc, din, instr);
	RegFile cpu_regs (clock, reset, instr[25:21], instr[20:16], instr[15:11], regWrite, out, rdA, rdB);
	ALU my_alu (out, zero, rdA, rdB, alu_ctrl);
	
	assign op = instr[31:26];
	assign func_code = instr [5:0];

endmodule

verilog lab7/ctrl_unit.v
`include "constants.h"

module Main_decoder (op, regWrite, alu_op);
	input [5:0] op;
	input regWrite;
	output reg [1:0] alu_op;

	always @(*)
		case (op)
			`R_FORMAT: alu_op <= 2'b10;	// R-FORMAT
			`LW: alu_op <= 2'b00;		// LW
			`SW: alu_op <= 2'b00;		// SW
			`BEQ: alu_op <= 2'b01;		// BEQ
			 default: alu_op <= 2'b11;  // NOP
		endcase
endmodule

module Alu_decoder (alu_op, func_code, alu_ctrl);

	input [1:0] alu_op;
	input [5:0] func_code;
	output reg [3:0] alu_ctrl;

	always @(*)
		case (func_code)
			6'b100100: alu_ctrl <= 4'b0000;	// and
			6'b100101: alu_ctrl <= 4'b0001;	// or
			6'b100000: alu_ctrl <= 4'b0010;	// add
			6'b100010: alu_ctrl <= 4'b0110;	// substract
			6'b101010: alu_ctrl <= 4'b0111;	// slt
			6'b100111: alu_ctrl <= 4'b1100;	// nor
		default: alu_ctrl <= 4'b1111; 		// we should never reach this place!!!!!!!!!!!
	endcase
endmodule

verilog lab7/lab7_testbench_input.v
// Define top-level testbench
// ~~~~~~~~~~~~~~~~~~~~~~~~~~~~~
// Top level has no inputs or outputs
// It only needs to instantiate CPU, Drive the inputs to CPU (clock, reset)
// and monitor the outputs. This is what all testbenches do

`include "constants.h"
`timescale 1ns/1ps
`define clock_period 2

module cpu_tb;
integer   i;
reg       clock, reset;    // Clock and reset signals

initial
	begin
		$dumpfile("lab7.vcd");
		$dumpvars(0, cpu_tb);
	end
// Instantiate CPU here with name cpu0
CPU cpu0 (clock, reset); 

// Initialization and signal generation
// ~~~~~~~~~~~~~~~~~~~~~~~~~~~~~~~~

// Generate clock and reset signal here
 
  // Initialize Register File with initial values. 
  // cpu0 is the name of the cpu instance
  // cpu_regs is the name of the register file instance in the CPU verilog file 
  // data[] is the register file array 
initial begin 
	
	clock = 1'b0;
	reset = 1'b0;
	
	#(`clock_period * 2) reset = 1'b1;
	
	
	for (i = 0; i < 32; i = i+1)
		cpu0.datapass.cpu_regs.data[i] = i;   // Note that R0 = 0 in MIPS 

  // Initialize Data Memory. You have to develop "program.hex" as a text file 
  // which containsthe instruction opcodes as 32-bit hexadecimal values.
  		$readmemh("program.hex", cpu0.datapass.mem.data);

  // Edw, to "program.hex" einai ena arxeio pou prepei na brisketai sto 
  // directory pou trexete th Verilog kai na einai ths morfhs:
  
  // @0    00000000
  // @4    20100009
  // @8    00000000
  // @C    00000000
  // ...
  
  // H aristerh sthlh, meta to @, exei th dieythynsh ths mnhmhs (hex),
  // kai h deksia sthlh ta dedomena sth dieythynsh ayth (pali hex).
  // Sto paradeigma pio panw, oi lekseis stis dieythynseis 0, 8 kai 12
  // einai 0, kai sth dieythynsh 4 exei thn timh 32'h20100009. An o PC
  // diabasei thn dieythynsh 4, h timh ekei exei thn entolh
  //   addi $16 <- $0 + 9

  // To deytero orisma ths $readmemh einai pou akribws brisketai h mnhmh
  // pou tha arxikopoihthei. Sto paradeigma, to "dat0" einai to onoma pou
  // dwsame sto instance tou datapath. To "mem" einai to onoma pou exei
  // to instance ths mnhmhs MESA sto datapath, kai to "data" einai to 
  // onoma pou exei to pragmatiko array ths mhnhs mesa sto module ths.
  // An exete dwsei diaforetika onomata, allakste thn $readmemh.

  // Enallaktika, an sas boleyei perissotero, yparxei h entolh $readmemb
  // me thn akribws idia syntaksh. H aristerh sthlh tou arxeiou exei
  // thn idia morfh (dieythynseis se hex), alla h deksia sthlh exei
  // ta dedomena sto dyadiko. Etsi h add mporouse na einai:

  // @4    00100000000100000000000000001001

  // ... h kai akoma kalytera:
  
  // @4    001000_00000_10000_0000000000001001

  // (h Verilog epitrepei diaxwristika underscores).

	
  // Termatismos ekteleshs:
	#(`clock_period * 40) $finish;

end  // initial 

always begin
	#(`clock_period/2) clock=~clock;
end
endmodule

verilog lab7/lab7.vcd
$date
	Sat Nov 30 19:08:47 2013
$end
$version
	Icarus Verilog
$end
$timescale
	1ps
$end
$scope module cpu_tb $end
$var reg 1 ! clock $end
$var integer 32 " i [31:0] $end
$var reg 1 # reset $end
$scope module cpu0 $end
$var wire 4 $ alu_ctrl [3:0] $end
$var wire 2 % alu_op [1:0] $end
$var wire 1 & clock $end
$var wire 6 ' func_code [5:0] $end
$var wire 6 ( op [5:0] $end
$var wire 1 ) regWrite $end
$var wire 1 * reset $end
$scope module dec_main $end
$var wire 6 + op [5:0] $end
$var wire 1 ) regWrite $end
$var reg 2 , alu_op [1:0] $end
$upscope $end
$scope module dec_alu $end
$var wire 2 - alu_op [1:0] $end
$var wire 6 . func_code [5:0] $end
$var reg 4 / alu_ctrl [3:0] $end
$upscope $end
$scope module datapass $end
$var wire 4 0 alu_ctrl [3:0] $end
$var wire 1 & clock $end
$var wire 32 1 din [31:0] $end
$var wire 6 2 func_code [5:0] $end
$var wire 32 3 instr [31:0] $end
$var wire 6 4 op [5:0] $end
$var wire 32 5 out [31:0] $end
$var wire 32 6 pc [31:0] $end
$var wire 32 7 pc_new [31:0] $end
$var wire 32 8 rdA [31:0] $end
$var wire 32 9 rdB [31:0] $end
$var wire 1 ) regWrite $end
$var wire 1 * reset $end
$var wire 1 : zero $end
$scope module reloaded_pc $end
$var wire 32 ; PC_new [31:0] $end
$var wire 1 & clock $end
$var wire 1 * reset $end
$var reg 32 < PC [31:0] $end
$upscope $end
$scope module additive $end
$var wire 32 = current [31:0] $end
$var wire 32 > next_pc [31:0] $end
$upscope $end
$scope module mem $end
$var wire 32 ? addr [31:0] $end
$var wire 1 & clock $end
$var wire 32 @ din [31:0] $end
$var wire 32 A dout [31:0] $end
$var wire 1 B ren $end
$var wire 1 * reset $end
$var wire 1 C wen $end
$upscope $end
$scope module cpu_regs $end
$var wire 1 & clock $end
$var wire 5 D raA [4:0] $end
$var wire 5 E raB [4:0] $end
$var wire 32 F rdA [31:0] $end
$var wire 32 G rdB [31:0] $end
$var wire 1 * reset $end
$var wire 5 H wa [4:0] $end
$var wire 32 I wd [31:0] $end
$var wire 1 ) wen $end
$var integer 32 J i [31:0] $end
$upscope $end
$scope module my_alu $end
$var wire 4 K alu_ctrl [3:0] $end
$var wire 32 L inA [31:0] $end
$var wire 32 M inB [31:0] $end
$var wire 1 : zero $end
$var reg 32 N out [31:0] $end
$upscope $end
$upscope $end
$upscope $end
$upscope $end
$enddefinitions $end
#0
$dumpvars
b0x N
bx M
bx L
b1111 K
b100000 J
b0x I
bx H
bx G
bx F
bx E
bx D
0C
1B
bx A
bz @
b0 ?
b100 >
b0 =
b0 <
b100 ;
x:
bx 9
bx 8
b100 7
b0 6
b0x 5
bx 4
bx 3
bx 2
bz 1
b1111 0
b1111 /
bx .
b11 -
b11 ,
bx +
0*
z)
bx (
bx '
0&
b11 %
b1111 $
0#
bx "
0!
$end
#1000
1!
1&
#2000
b100000 J
0!
0&
#3000
1!
1&
#4000
b11000 N
0:
b11000 5
b11000 I
b10 /
b10 $
b10 0
b10 K
b10 ,
b10 %
b10 -
b100000 '
b100000 .
b100000 2
b0 (
b0 +
b0 4
b1000 H
b10000 E
b10000 9
b10000 G
b10000 M
b1000 D
b1000 8
b1000 F
b1000 L
b1000100000100000000100000 3
b1000100000100000000100000 A
0!
0&
b100000 "
1#
1*
#5000
b110 /
b110 $
b110 0
b110 K
b101 N
b101 5
b101 I
b100010 '
b100010 .
b100010 2
b1001 H
b100 E
b100 9
b100 G
b100 M
b1001 D
b1001 8
b1001 F
b1001 L
b1001001000100100000100010 3
b1001001000100100000100010 A
b1000 7
b1000 ;
b1000 >
b100 <
b100 6
b100 =
b100 ?
1!
1&
#6000
0!
0&
#7000
b1 /
b1 $
b1 0
b1 K
b1111 N
b1111 5
b1111 I
b100101 '
b100101 .
b100101 2
b1111 H
b1101 E
b1101 9
b1101 G
b1101 M
b1111 D
b1111 8
b1111 F
b1111 L
b1111011010111100000100101 3
b1111011010111100000100101 A
b1100 7
b1100 ;
b1100 >
b1000 <
b1000 6
b1000 =
b1000 ?
1!
1&
#8000
0!
0&
#9000
b0 /
b0 $
b0 0
b0 K
b10000 N
b10000 5
b10000 I
b100100 '
b100100 .
b100100 2
b10001 H
b10010 E
b10010 9
b10010 G
b10010 M
b10000 D
b10000 8
b10000 F
b10000 L
b10000100101000100000100100 3
b10000100101000100000100100 A
b10000 7
b10000 ;
b10000 >
b1100 <
b1100 6
b1100 =
b1100 ?
1!
1&
#10000
0!
0&
#11000
1:
b111 /
b111 $
b111 0
b111 K
b0 N
b0 5
b0 I
b101010 '
b101010 .
b101010 2
b10010 H
b1111 E
b1111 9
b1111 G
b1111 M
b10001 D
b10001 8
b10001 F
b10001 L
b10001011111001001000101010 3
b10001011111001001000101010 A
b10100 7
b10100 ;
b10100 >
b10000 <
b10000 6
b10000 =
b10000 ?
1!
1&
#12000
0!
0&
#13000
b11000 N
0:
b11000 5
b11000 I
b10 /
b10 $
b10 0
b10 K
b100000 '
b100000 .
b100000 2
b1111 H
b1100 E
b1100 9
b1100 G
b1100 M
b1100 D
b1100 8
b1100 F
b1100 L
b1100011000111100000100000 3
b1100011000111100000100000 A
b11000 7
b11000 ;
b11000 >
b10100 <
b10100 6
b10100 =
b10100 ?
1!
1&
#14000
0!
0&
#15000
b111 /
b111 $
b111 0
b111 K
b1 N
b1 5
b1 I
b101010 '
b101010 .
b101010 2
b1101 E
b1101 9
b1101 G
b1101 M
b1100011010111100000101010 3
b1100011010111100000101010 A
b11100 7
b11100 ;
b11100 >
b11000 <
b11000 6
b11000 =
b11000 ?
1!
1&
#16000
0!
0&
#17000
b1111 /
b1111 $
b1111 0
b1111 K
b11 ,
b11 %
b11 -
b0x N
x:
b0x 5
b0x I
bx '
bx .
bx 2
bx (
bx +
bx 4
bx H
bx E
bx 9
bx G
bx M
bx D
bx 8
bx F
bx L
bx 3
bx A
b100000 7
b100000 ;
b100000 >
b11100 <
b11100 6
b11100 =
b11100 ?
1!
1&
#18000
0!
0&
#19000
b100100 7
b100100 ;
b100100 >
b100000 <
b100000 6
b100000 =
b100000 ?
1!
1&
#20000
0!
0&
#21000
b101000 7
b101000 ;
b101000 >
b100100 <
b100100 6
b100100 =
b100100 ?
1!
1&
#22000
0!
0&
#23000
b101100 7
b101100 ;
b101100 >
b101000 <
b101000 6
b101000 =
b101000 ?
1!
1&
#24000
0!
0&
#25000
b110000 7
b110000 ;
b110000 >
b101100 <
b101100 6
b101100 =
b101100 ?
1!
1&
#26000
0!
0&
#27000
b110100 7
b110100 ;
b110100 >
b110000 <
b110000 6
b110000 =
b110000 ?
1!
1&
#28000
0!
0&
#29000
b111000 7
b111000 ;
b111000 >
b110100 <
b110100 6
b110100 =
b110100 ?
1!
1&
#30000
0!
0&
#31000
b111100 7
b111100 ;
b111100 >
b111000 <
b111000 6
b111000 =
b111000 ?
1!
1&
#32000
0!
0&
#33000
b1000000 7
b1000000 ;
b1000000 >
b111100 <
b111100 6
b111100 =
b111100 ?
1!
1&
#34000
0!
0&
#35000
b1000100 7
b1000100 ;
b1000100 >
b1000000 <
b1000000 6
b1000000 =
b1000000 ?
1!
1&
#36000
0!
0&
#37000
b1001000 7
b1001000 ;
b1001000 >
b1000100 <
b1000100 6
b1000100 =
b1000100 ?
1!
1&
#38000
0!
0&
#39000
b1001100 7
b1001100 ;
b1001100 >
b1001000 <
b1001000 6
b1001000 =
b1001000 ?
1!
1&
#40000
0!
0&
#41000
b1010000 7
b1010000 ;
b1010000 >
b1001100 <
b1001100 6
b1001100 =
b1001100 ?
1!
1&
#42000
0!
0&
#43000
b1010100 7
b1010100 ;
b1010100 >
b1010000 <
b1010000 6
b1010000 =
b1010000 ?
1!
1&
#44000
0!
0&
#45000
b1011000 7
b1011000 ;
b1011000 >
b1010100 <
b1010100 6
b1010100 =
b1010100 ?
1!
1&
#46000
0!
0&
#47000
b1011100 7
b1011100 ;
b1011100 >
b1011000 <
b1011000 6
b1011000 =
b1011000 ?
1!
1&
#48000
0!
0&
#49000
b1100000 7
b1100000 ;
b1100000 >
b1011100 <
b1011100 6
b1011100 =
b1011100 ?
1!
1&
#50000
0!
0&
#51000
b1100100 7
b1100100 ;
b1100100 >
b1100000 <
b1100000 6
b1100000 =
b1100000 ?
1!
1&
#52000
0!
0&
#53000
b1101000 7
b1101000 ;
b1101000 >
b1100100 <
b1100100 6
b1100100 =
b1100100 ?
1!
1&
#54000
0!
0&
#55000
b1101100 7
b1101100 ;
b1101100 >
b1101000 <
b1101000 6
b1101000 =
b1101000 ?
1!
1&
#56000
0!
0&
#57000
b1110000 7
b1110000 ;
b1110000 >
b1101100 <
b1101100 6
b1101100 =
b1101100 ?
1!
1&
#58000
0!
0&
#59000
b1110100 7
b1110100 ;
b1110100 >
b1110000 <
b1110000 6
b1110000 =
b1110000 ?
1!
1&
#60000
0!
0&
#61000
b1111000 7
b1111000 ;
b1111000 >
b1110100 <
b1110100 6
b1110100 =
b1110100 ?
1!
1&
#62000
0!
0&
#63000
b1111100 7
b1111100 ;
b1111100 >
b1111000 <
b1111000 6
b1111000 =
b1111000 ?
1!
1&
#64000
0!
0&
#65000
b10000000 7
b10000000 ;
b10000000 >
b1111100 <
b1111100 6
b1111100 =
b1111100 ?
1!
1&
#66000
0!
0&
#67000
b10000100 7
b10000100 ;
b10000100 >
b10000000 <
b10000000 6
b10000000 =
b10000000 ?
1!
1&
#68000
0!
0&
#69000
b10001000 7
b10001000 ;
b10001000 >
b10000100 <
b10000100 6
b10000100 =
b10000100 ?
1!
1&
#70000
0!
0&
#71000
b10001100 7
b10001100 ;
b10001100 >
b10001000 <
b10001000 6
b10001000 =
b10001000 ?
1!
1&
#72000
0!
0&
#73000
b10010000 7
b10010000 ;
b10010000 >
b10001100 <
b10001100 6
b10001100 =
b10001100 ?
1!
1&
#74000
0!
0&
#75000
b10010100 7
b10010100 ;
b10010100 >
b10010000 <
b10010000 6
b10010000 =
b10010000 ?
1!
1&
#76000
0!
0&
#77000
b10011000 7
b10011000 ;
b10011000 >
b10010100 <
b10010100 6
b10010100 =
b10010100 ?
1!
1&
#78000
0!
0&
#79000
b10011100 7
b10011100 ;
b10011100 >
b10011000 <
b10011000 6
b10011000 =
b10011000 ?
1!
1&
#80000
0!
0&
#81000
b10100000 7
b10100000 ;
b10100000 >
b10011100 <
b10011100 6
b10011100 =
b10011100 ?
1!
1&
#82000
0!
0&
#83000
b10100100 7
b10100100 ;
b10100100 >
b10100000 <
b10100000 6
b10100000 =
b10100000 ?
1!
1&
