verilog lab8_final/library_input.v

`timescale 1ns/1ps


///////////////////////////////////////////////////////////////////////////////////
//~~~~~~~~~~~~~~~~~~~~~~~~~~~~~~~~~ ALU ~~~~~~~~~~~~~~~~~~~~~~~~~~~~~~~~~~~~~~~~~~//
//																				  //
// Small ALU. Inputs: inA, inB. Output: out. 									  //
// Operations: bitwise and (op = 0)												  //
//             bitwise or  (op = 1)												  //
//             addition (op = 2)												  //
//             subtraction (op = 6)												  //
//             slt  (op = 7)													  //
//             nor (op = 12)													  //
////////////////////////////////////////////////////////////////////////////////////

module ALU (out, zero, inA, inB, alu_ctrl);

  input [3:0] alu_ctrl;
  input [31:0] inA, inB;
  output reg [31:0] out;
  output wire zero;
  
  assign zero = out ? 0 : 1;
  
  always @ (alu_ctrl, inA, inB) begin
    
    case (alu_ctrl)
      4'b0000: out <= inA&inB;
      4'b0001: out <= inA | inB;       	// or
      4'b0010: out <= inA + inB;       	// add
      4'b0110: out <= inA - inB;       	// substract
      4'b0111: out <= inA < inB ? 1:0; 	// slt
      4'b1100: out <= ~(inA | inB);		// nor
      default: out <= 'bx;
    endcase
  end
  
endmodule

///////////////////////////////////////////////////////////////////////////////////
//~~~~~~~~~~~~~~~~~~~~~~~~~~~~~ Program Counter ~~~~~~~~~~~~~~~~~~~~~~~~~~~~~~~~//
//																				//
// 				Sets the new program counter as the current pc					//
//																				//
//////////////////////////////////////////////////////////////////////////////////

module ProgramCounter (clock, reset, PC_new, PC);

	input reset, clock;
	input [31:0] PC_new;
	output reg [31:0] PC;

	always @(posedge clock or negedge reset)
		begin
			if (reset == 1'b0)	// an to reset einai 0 krata 0 kai ton program counter
				PC <= 32'h0;
			else
				PC <= PC_new;	// alliws dwse ston trexon pc timh ish me thn epomenh dieu8unsh
		end

endmodule

///////////////////////////////////////////////////////////////////////////////////
//~~~~~~~~~~~~~~~~~~~~~~~~~~~~~~~~ Memory ~~~~~~~~~~~~~~~~~~~~~~~~~~~~~~~~~~~~~~//
//																				//
// 		Memory (active 1024 words, from 10 address lsbs).						//
//      Read : enable ren, address addr, data dout								//
//      Write: enable wen, address addr, data din.								//
//																				//
//////////////////////////////////////////////////////////////////////////////////

module Memory (ren, wen, addr, din, dout);
  input		ren, wen, clock;
  input		[31:0] addr, din;
  output	[31:0] dout;

  reg [31:0] data[4095:0];
  wire [31:0] dout;

  always @(ren or wen)
    if (ren & wen)
      $display ("\nMemory ERROR (time %0d): ren and wen both active!\n", $time);

  always @(posedge ren or posedge wen) begin
    if (addr[31:10] != 0)
      $display("Memory WARNING (time %0d): address msbs are not zero\n", $time);
  end  

  assign dout = ((wen==1'b0) && (ren==1'b1)) ? data[addr[9:0]] : 32'bx;
  
  always @(wen or ren or addr)
   begin
    if ((wen == 1'b1) && (ren==1'b0))
        data[addr[9:0]] = din;
   end

endmodule

///////////////////////////////////////////////////////////////////////////////////
//~~~~~~~~~~~~~~~~~~~~~~~~~~~~~~~Register File ~~~~~~~~~~~~~~~~~~~~~~~~~~~~~~~~~~//
//																				 //
// 		Read ports: address raA, data rdA										 //
//                          address raB, data rdB								 //
//      Write port: address wa, data wd, enable wen.							 //
//																				 //
///////////////////////////////////////////////////////////////////////////////////

module RegFile (clock, reset, raA, raB, wa, wen, wd, rdA, rdB);


	output wire [31:0] rdA, rdB;
	input [31:0] wd;
	input [4:0] raA, raB, wa;
	input wen, reset, clock;
	reg [31:0] data [31:0];
	integer i;


	assign rdA = data[raA];
	assign rdB = data[raB];
	// Write Section
	always @(negedge clock or negedge reset)	// the register file should be written at 
		begin								// the negative edge of the input clock

			if (reset==1'b0)
	  			for(i=0;i<32;i=i+1)
					data[i] <= i;		//otan to reset einai 0 mhdenizw olous ts kataxwrhtes
			else if (wen==1'b1)		// alliws dwse ston ka8e kataxwrhth timh idia me
				data[wa] <= wd;  	// idia me ton au3oda ari8mo tu
		end


endmodule

///////////////////////////////////////////////////////////////////////////////////
//~~~~~~~~~~~~~~~~~~~~~~~~~~~~~~~~ ADDER ~~~~~~~~~~~~~~~~~~~~~~~~~~~~~~~~~~~~~~~~~//
//																				  //
// 					Adds 4 bytes to move to the next instruction				  //
//																				  //
////////////////////////////////////////////////////////////////////////////////////

module Adder (current, next_pc);

	parameter step = 32'h4;
	input [31:0] current;
	output wire [31:0] next_pc;

	assign next_pc = current + step;
	
endmodule

////////////////////////////////////////////////////////////////////////////////////
//~~~~~~~~~~~~~~~~~~~~~~~~~~~~~~~~ ADDER2 ~~~~~~~~~~~~~~~~~~~~~~~~~~~~~~~~~~~~~~~~//
//																				  //
// 					Adds 4 bytes to shifted instruction							  //
//																				  //
////////////////////////////////////////////////////////////////////////////////////

module Adder2 (shifted_instr, next_pc, next_instr);

	input [31:0] shifted_instr, next_pc;
	output wire [31:0] next_instr;

	assign next_instr = shifted_instr + next_pc;
	
endmodule



///////////////////////////////////////////////////////////////////////////////////
//~~~~~~~~~~~~~~~~~~~~~~~~~~~~~~ SignExtend ~~~~~~~~~~~~~~~~~~~~~~~~~~~~~~~~~~~~~~//
//																				  //
// 					A module that extends the sign and adds zero				  //
//							   at the 2 LSB										  //
//																				  //
////////////////////////////////////////////////////////////////////////////////////

module SignExtend (instr, extended_instr);

	input[15:0] instr;
	output wire [31:0] extended_instr;
	
    assign extended_instr = {{16{instr[15]}}, instr[15:0]};

endmodule


///////////////////////////////////////////////////////////////////////////////////
//~~~~~~~~~~~~~~~~~~~~~~~~~~~~~~~~ Sifter ~~~~~~~~~~~~~~~~~~~~~~~~~~~~~~~~~~~~~~~~//
//																				  //
// 					A module that shifts left the LSB bits						  //
//																				  //
////////////////////////////////////////////////////////////////////////////////////

module Sifter (extended_instr, shifted_instr);

	input [31:0] extended_instr;
	output wire [31:0] shifted_instr;
	
	assign shifted_instr = extended_instr << 2;	
	
endmodule

////////////////////////////////////////////////////////////////////////////////////
//~~~~~~~~~~~~~~~~~~~~~~~~~~~~~~~~~ AND ~~~~~~~~~~~~~~~~~~~~~~~~~~~~~~~~~~~~~~~~~~//
//																				  //
// 							A simple 'and' gate									  //
//																				  //
////////////////////////////////////////////////////////////////////////////////////


module AND (zero, branch, select_signal);
	input zero;
	input branch;
	output wire select_signal;
	
	assign select_signal = zero & branch;

endmodule


///////////////////////////////////////////////////////////////////////////////////
//~~~~~~~~~~~~~~~~~~~~~~~~~~~~ Multiplexers ~~~~~~~~~~~~~~~~~~~~~~~~~~~~~~~~~~~~~~//
//																				  //
// 					Four modules for each multiplexers in the circuit			  //
//																				  //
////////////////////////////////////////////////////////////////////////////////////


module MultiPlx_Ctrl_Reg (select, input1, input2, out);

	input [4:0] input1, input2;
	input select;
	output wire [4:0] out;
	
	assign out = (select==1'b1) ? input2 : input1;
	
endmodule


module MultiPlx_Add2_PC (select_signal, new_instr, next_pc, new_program_counter);

	input select_signal;
	input [31:0] new_instr, next_pc;
	output wire [31:0] new_program_counter;
	
	assign new_program_counter = (select_signal==1'b1) ? next_pc : new_instr;
	
endmodule


module MultiPlx_Reg_ALU (AluSrc, rdB, extended_instr, inB);

	input AluSrc;
	input [31:0] rdB, extended_instr;
	output wire [31:0] inB;
	
	assign inB = (AluSrc==1'b1) ? extended_instr : rdB;
	
endmodule


module MultiPlx_Mem_Reg (MemReg, dout, out, wd);
	
	input MemReg;
	input [31:0] dout, out;
	output wire [31:0] wd;
	
	assign wd = (MemReg==1'b1) ? out : dout;
	
endmodule

///////////////////////////////////////////////////////////////////////////////////
//~~~~~~~~~~~~~~~~~~~~~~~~~~~~~~~~~~ CPU ~~~~~~~~~~~~~~~~~~~~~~~~~~~~~~~~~~~~~~~~~//
//																				  //
// 					A module that describes the function of cpu					  //
//																				  //
////////////////////////////////////////////////////////////////////////////////////
                                                                                  
module CPU (clock, reset);

	input clock, reset;
	wire [1:0] alu_op, Branch;
	wire RegWrite, RegDst, AluSrc, MemWrite, MemReg, MemRead;
	wire [3:0] alu_ctrl;
	wire [5:0] op, func_code;
	
	// enwnoume to FSM me ta upoloipa stoixeia //
	Main_decoder	dec_main	(op, RegWrite, alu_op, RegDst, AluSrc, Branch, MemWrite, MemReg, MemRead);
	Alu_decoder		dec_alu		(alu_op, func_code, alu_ctrl);
	data_path		datapass 	(clock, reset, RegWrite, alu_ctrl, op, func_code, RegDst, AluSrc, Branch, MemWrite, MemReg, MemRead);

endmodule

verilog lab8_final/data_path.v

`timescale 1ns/1ps

module data_path (clock, reset, RegWrite, alu_ctrl, op, func_code, RegDist, AluSrc, Branch, MemWrite, MemReg, MemRead);

	input clock, reset;
	input RegWrite, RegDist, AluSrc, MemWrite, MemReg, MemRead;
	input [3:0] alu_ctrl;
	input [1:0] Branch;
	output [5:0] op, func_code;
	
	wire [31:0] instr, added_pc, pc_new, pc, rdA, rdB, din, wd, alu_out, adder2_out;
	wire [31:0] extended_instr, shifted_instr, mem_out, out_multi3;
	wire [4:0] out_multi1;
	wire and_out, zero;
	reg zero_input, branch_type;

	always@(*)
		begin
			case(Branch)
				2'b00: 	begin					// NO BRANCH
							branch_type = 1'b0;
							zero_input = zero;
						end
				2'b10: 	begin					// BNE
							branch_type = 1'b1;
							zero_input = ~zero;
						end
				2'b11: 	begin					// BEQ
							branch_type = 1'b1;
							zero_input = zero;
						end
				default: begin 
							if (reset)
								$display ("Wrong Branch Instruction");
						end
			endcase
		end
	// enwnoume ola ta stoixeia //
	ProgramCounter	reloaded_pc	(clock, reset, pc_new, pc);
	Adder			additive	(pc, added_pc);
	
	Memory			mem_INSTR 	(1'b1, 1'b0, pc, 32'b0, instr);
	RegFile			cpu_regs	(clock, reset, instr[25:21], instr[20:16], out_multi1, RegWrite, wd, rdA, rdB);
	AND				and_gate	(zero_input, branch_type, and_out);
	SignExtend		extended 	(instr[15:0], extended_instr);
	Sifter			sifted		(extended_instr, shifted_instr);
	Adder2			adder2 		(shifted_instr, added_pc, adder2_out);
	
	MultiPlx_Ctrl_Reg multi1 	(RegDist, instr[20:16], instr[15:11], out_multi1);
	MultiPlx_Add2_PC  multi2 	(and_out, added_pc, adder2_out, pc_new);
	MultiPlx_Reg_ALU  multi3 	(AluSrc, rdB, extended_instr, out_multi3);
	MultiPlx_Mem_Reg  multi4 	(MemReg, alu_out, mem_out, wd);
	
	ALU 			my_alu 		(alu_out, zero, rdA, out_multi3, alu_ctrl);
	Memory 			mem_DATA 	(MemRead, MemWrite, alu_out, rdB, mem_out);
	
	assign op = instr[31:26];
	assign func_code = instr [5:0];

endmodule

verilog lab8_final/ctrl_unit.v
`include "constants.h"
`timescale 1ns/1ps

module Main_decoder (op, RegWrite, alu_op, RegDist, AluSrc, Branch, MemWrite, MemReg, MemRead);
	input [5:0] op;
	output reg [1:0] alu_op, Branch;
	output reg RegDist, RegWrite, AluSrc, MemWrite, MemReg, MemRead;

	always @(*)
		case (op)
			`R_FORMAT: 
				begin
					alu_op <= 2'b10;

					RegWrite <= 1'b1;
					RegDist <= 1'b1;
					AluSrc <= 1'b0;
					Branch <= 2'b00;
					MemWrite <= 1'b0;
					MemReg <= 1'b0;
					MemRead <= 1'b0;
				end
			`LW: 
				begin
					alu_op <= 2'b00;

					RegWrite <= 1'b1;
					RegDist <= 1'b0;
					AluSrc <= 1'b1;
					Branch <= 2'b00;
					MemWrite <= 1'b0;
					MemReg <= 1'b1;
					MemRead <= 1'b1;
				end
			`SW: 
				begin
					alu_op <= 2'b00;

					RegWrite <= 1'b0;
					RegDist <= 1'bx;
					AluSrc <= 1'b1;
					Branch <= 2'b00;
					MemWrite <= 1'b1;
					MemReg <= 1'bx;
					MemRead <= 1'b0;
				end
			`BEQ: 
				begin
					alu_op <= 2'b01;

					RegWrite <= 1'b0;
					RegDist <= 1'bx;
					AluSrc <= 1'b0;
					Branch <= 2'b11;
					MemWrite <= 1'b0; 
					MemReg <= 1'bx;
					MemRead <= 1'b0;
				end
			`BNE: 
				begin
					alu_op <= 2'b01;

					RegWrite <= 1'b0;
					RegDist <= 1'bx;
					AluSrc <= 1'b0;
					Branch <= 2'b10;
					MemWrite <= 1'b0; 
					MemReg <= 1'bx;
					MemRead <= 1'b0;
				end
			 default: alu_op <= 2'b11;  // ~NOP~ we should never reach this place
		endcase
endmodule

module Alu_decoder (alu_op, func_code, alu_ctrl);

	input [1:0] alu_op;
	input [5:0] func_code;
	output reg [3:0] alu_ctrl;

	always @(*)
		case (alu_op)
		2'b00: alu_ctrl <= 4'b0010; // if lw or sw then add
		2'b01: alu_ctrl <= 4'b0110;	// if beq or bne then sub
		2'b10:
			case (func_code)
				6'b100100: alu_ctrl <= 4'b0000;	// and
				6'b100101: alu_ctrl <= 4'b0001;	// or
				6'b100000: alu_ctrl <= 4'b0010;	// add
				6'b100010: alu_ctrl <= 4'b0110;	// substract
				6'b101010: alu_ctrl <= 4'b0111;	// slt
				6'b100111: alu_ctrl <= 4'b1100;	// nor
				default: alu_ctrl <= 4'b1111; 		// we should never reach this place!!!!!!!!!!!
			endcase
		default: alu_ctrl <= 4'b1111;
	endcase
endmodule

verilog lab8_final/testbench_input.v
// Define top-level testbench
// ~~~~~~~~~~~~~~~~~~~~~~~~~~~~~
// Top level has no inputs or outputs
// It only needs to instantiate CPU, Drive the inputs to CPU (clock, reset)
// and monitor the outputs. This is what all testbenches do

`include "constants.h"
`timescale 1ns/1ps
`define clock_period 10

module cpu_tb;
integer   i;
reg       clock, reset;    // Clock and reset signals

// Instantiate CPU here with name cpu0
CPU cpu0 (clock, reset); 

// Initialization and signal generation
// ~~~~~~~~~~~~~~~~~~~~~~~~~~~~~~~~

// Generate clock and reset signal here
 
  // Initialize Register File with initial values. 
  // cpu0 is the name of the cpu instance
  // cpu_regs is the name of the register file instance in the CPU verilog file 
  // data[] is the register file array 
initial begin 

	$dumpfile("lab8.vcd");
	$dumpvars(0, cpu_tb);
	clock = 1'b0;
	reset = 1'b0;

  // Initialize Data Memory. You have to develop "program.hex" as a text file 
  // which containsthe instruction opcodes as 32-bit hexadecimal values.
	for (i=0; i<4095; i=i+1)
		cpu0.datapass.mem_DATA.data[i]=32'b0;
	$readmemb("code2.mbin", cpu0.datapass.mem_INSTR.data);
	#(`clock_period*4) reset = 1'b1;

  // Edw, to "program.hex" einai ena arxeio pou prepei na brisketai sto 
  // directory pou trexete th Verilog kai na einai ths morfhs:
  
  // @0    00000000
  // @4    20100009
  // @8    00000000
  // @C    00000000
  // ...
  
  // H aristerh sthlh, meta to @, exei th dieythynsh ths mnhmhs (hex),
  // kai h deksia sthlh ta dedomena sth dieythynsh ayth (pali hex).
  // Sto paradeigma pio panw, oi lekseis stis dieythynseis 0, 8 kai 12
  // einai 0, kai sth dieythynsh 4 exei thn timh 32'h20100009. An o PC
  // diabasei thn dieythynsh 4, h timh ekei exei thn entolh
  //   addi $16 <- $0 + 9

  // To deytero orisma ths $readmemh einai pou akribws brisketai h mnhmh
  // pou tha arxikopoihthei. Sto paradeigma, to "dat0" einai to onoma pou
  // dwsame sto instance tou datapath. To "mem" einai to onoma pou exei
  // to instance ths mnhmhs MESA sto datapath, kai to "data" einai to 
  // onoma pou exei to pragmatiko array ths mhnhs mesa sto module ths.
  // An exete dwsei diaforetika onomata, allakste thn $readmemh.

  // Enallaktika, an sas boleyei perissotero, yparxei h entolh $readmemb
  // me thn akribws idia syntaksh. H aristerh sthlh tou arxeiou exei
  // thn idia morfh (dieythynseis se hex), alla h deksia sthlh exei
  // ta dedomena sto dyadiko. Etsi h add mporouse na einai:

  // @4    00100000000100000000000000001001

  // ... h kai akoma kalytera:
  
  // @4    001000_00000_10000_0000000000001001

  // (h Verilog epitrepei diaxwristika underscores).

	
  // Termatismos ekteleshs:
	#(`clock_period * 40) $finish;

end  // initial 

always begin
	#(`clock_period/0.5) clock=~clock;
end
endmodule

verilog lab8_final/lab8.vcd
$date
	Thu Dec 12 15:04:33 2013
$end
$version
	Icarus Verilog
$end
$timescale
	1ps
$end
$scope module cpu_tb $end
$var reg 1 ! clock $end
$var integer 32 " i [31:0] $end
$var reg 1 # reset $end
$scope module cpu0 $end
$var wire 1 $ AluSrc $end
$var wire 2 % Branch [1:0] $end
$var wire 1 & MemRead $end
$var wire 1 ' MemReg $end
$var wire 1 ( MemWrite $end
$var wire 1 ) RegDst $end
$var wire 1 * RegWrite $end
$var wire 4 + alu_ctrl [3:0] $end
$var wire 2 , alu_op [1:0] $end
$var wire 1 - clock $end
$var wire 6 . func_code [5:0] $end
$var wire 6 / op [5:0] $end
$var wire 1 0 reset $end
$scope module dec_main $end
$var wire 6 1 op [5:0] $end
$var reg 1 2 AluSrc $end
$var reg 2 3 Branch [1:0] $end
$var reg 1 4 MemRead $end
$var reg 1 5 MemReg $end
$var reg 1 6 MemWrite $end
$var reg 1 7 RegDist $end
$var reg 1 8 RegWrite $end
$var reg 2 9 alu_op [1:0] $end
$upscope $end
$scope module dec_alu $end
$var wire 2 : alu_op [1:0] $end
$var wire 6 ; func_code [5:0] $end
$var reg 4 < alu_ctrl [3:0] $end
$upscope $end
$scope module datapass $end
$var wire 1 $ AluSrc $end
$var wire 2 = Branch [1:0] $end
$var wire 1 & MemRead $end
$var wire 1 ' MemReg $end
$var wire 1 ( MemWrite $end
$var wire 1 ) RegDist $end
$var wire 1 * RegWrite $end
$var wire 32 > added_pc [31:0] $end
$var wire 32 ? adder2_out [31:0] $end
$var wire 4 @ alu_ctrl [3:0] $end
$var wire 32 A alu_out [31:0] $end
$var wire 1 B and_out $end
$var wire 1 - clock $end
$var wire 32 C extended_instr [31:0] $end
$var wire 6 D func_code [5:0] $end
$var wire 32 E instr [31:0] $end
$var wire 32 F mem_out [31:0] $end
$var wire 6 G op [5:0] $end
$var wire 5 H out_multi1 [4:0] $end
$var wire 32 I out_multi3 [31:0] $end
$var wire 32 J pc [31:0] $end
$var wire 32 K pc_new [31:0] $end
$var wire 32 L rdA [31:0] $end
$var wire 32 M rdB [31:0] $end
$var wire 1 0 reset $end
$var wire 32 N shifted_instr [31:0] $end
$var wire 32 O wd [31:0] $end
$var wire 1 P zero $end
$var reg 1 Q branch_type $end
$var reg 1 R zero_input $end
$scope module reloaded_pc $end
$var wire 32 S PC_new [31:0] $end
$var wire 1 - clock $end
$var wire 1 0 reset $end
$var reg 32 T PC [31:0] $end
$upscope $end
$scope module additive $end
$var wire 32 U current [31:0] $end
$var wire 32 V next_pc [31:0] $end
$upscope $end
$scope module mem_INSTR $end
$var wire 32 W addr [31:0] $end
$var wire 1 X clock $end
$var wire 32 Y din [31:0] $end
$var wire 32 Z dout [31:0] $end
$var wire 1 [ ren $end
$var wire 1 \ wen $end
$upscope $end
$scope module cpu_regs $end
$var wire 1 - clock $end
$var wire 5 ] raA [4:0] $end
$var wire 5 ^ raB [4:0] $end
$var wire 32 _ rdA [31:0] $end
$var wire 32 ` rdB [31:0] $end
$var wire 1 0 reset $end
$var wire 5 a wa [4:0] $end
$var wire 32 b wd [31:0] $end
$var wire 1 * wen $end
$var integer 32 c i [31:0] $end
$upscope $end
$scope module and_gate $end
$var wire 1 d branch $end
$var wire 1 B select_signal $end
$var wire 1 e zero $end
$upscope $end
$scope module extended $end
$var wire 32 f extended_instr [31:0] $end
$var wire 16 g instr [15:0] $end
$upscope $end
$scope module sifted $end
$var wire 32 h extended_instr [31:0] $end
$var wire 32 i shifted_instr [31:0] $end
$upscope $end
$scope module adder2 $end
$var wire 32 j next_instr [31:0] $end
$var wire 32 k next_pc [31:0] $end
$var wire 32 l shifted_instr [31:0] $end
$upscope $end
$scope module multi1 $end
$var wire 5 m input1 [4:0] $end
$var wire 5 n input2 [4:0] $end
$var wire 5 o out [4:0] $end
$var wire 1 ) select $end
$upscope $end
$scope module multi2 $end
$var wire 32 p new_instr [31:0] $end
$var wire 32 q new_program_counter [31:0] $end
$var wire 32 r next_pc [31:0] $end
$var wire 1 B select_signal $end
$upscope $end
$scope module multi3 $end
$var wire 1 $ AluSrc $end
$var wire 32 s extended_instr [31:0] $end
$var wire 32 t inB [31:0] $end
$var wire 32 u rdB [31:0] $end
$upscope $end
$scope module multi4 $end
$var wire 1 ' MemReg $end
$var wire 32 v dout [31:0] $end
$var wire 32 w out [31:0] $end
$var wire 32 x wd [31:0] $end
$upscope $end
$scope module my_alu $end
$var wire 4 y alu_ctrl [3:0] $end
$var wire 32 z inA [31:0] $end
$var wire 32 { inB [31:0] $end
$var wire 1 P zero $end
$var reg 32 | out [31:0] $end
$upscope $end
$scope module mem_DATA $end
$var wire 32 } addr [31:0] $end
$var wire 1 ~ clock $end
$var wire 32 !" din [31:0] $end
$var wire 32 "" dout [31:0] $end
$var wire 1 & ren $end
$var wire 1 ( wen $end
$upscope $end
$upscope $end
$upscope $end
$upscope $end
$enddefinitions $end
#0
$dumpvars
bx ""
b100 !"
z~
b1100 }
b1100 |
b100 {
b1000 z
b10 y
b1100 x
bx w
b1100 v
b100 u
b100 t
b100100000100000 s
b10010000010000100 r
b100 q
b100 p
b1001 o
b1001 n
b100 m
b10010000010000000 l
b100 k
b10010000010000100 j
b10010000010000000 i
b100100000100000 h
b100100000100000 g
b100100000100000 f
0e
0d
b100000 c
b1100 b
b1001 a
b100 `
b1000 _
b100 ^
b1000 ]
0\
1[
b1000001000100100000100000 Z
b0 Y
zX
b0 W
b100 V
b0 U
b0 T
b100 S
0R
0Q
0P
b1100 O
b10010000010000000 N
b100 M
b1000 L
b100 K
b0 J
b100 I
b1001 H
b0 G
bx F
b1000001000100100000100000 E
b100000 D
b100100000100000 C
0B
b1100 A
b10 @
b10010000010000100 ?
b100 >
b0 =
b10 <
b100000 ;
b10 :
b10 9
18
17
06
05
04
b0 3
02
b0 1
00
b0 /
b100000 .
0-
b10 ,
b10 +
1*
1)
0(
0'
0&
b0 %
0$
0#
b111111111111 "
0!
$end
#20000
1!
1-
#40000
0!
0-
1#
10
#60000
0R
0e
0P
bx O
bx b
bx x
b10 <
b10 +
b10 @
b10 y
x5
x'
16
1(
12
1$
x7
x)
08
0*
b0 9
b0 ,
b0 :
b10000 |
b10000 A
b10000 v
b10000 }
b0x00x H
b0x00x a
b0x00x o
b10100 N
b10100 i
b10100 l
b101 I
b101 t
b101 {
b101 .
b101 ;
b101 D
b101011 /
b101011 1
b101011 G
b0 n
b1001 m
b101 g
b101 C
b101 f
b101 h
b101 s
b1001 ^
b1100 M
b1100 `
b1100 u
b1100 !"
b1011 ]
b1011 L
b1011 _
b1011 z
b1000 K
b1000 S
b1000 q
b10101101011010010000000000000101 E
b10101101011010010000000000000101 Z
b11100 ?
b11100 j
b11100 r
b1000 >
b1000 V
b1000 k
b1000 p
b100 T
b100 J
b100 U
b100 W
1!
1-
#80000
0!
0-
#100000
b1100 O
b1100 b
b1100 x
b1100 F
b1100 w
b1100 ""
14
1&
15
1'
06
0(
07
0)
18
1*
b10010 H
b10010 a
b10010 o
b100011 /
b100011 1
b100011 G
b10010 m
b10010 ^
b10010 M
b10010 `
b10010 u
b10010 !"
b1100 K
b1100 S
b1100 q
b10001101011100100000000000000101 E
b10001101011100100000000000000101 Z
b100000 ?
b100000 j
b100000 r
b1100 >
b1100 V
b1100 k
b1100 p
b1000 T
b1000 J
b1000 U
b1000 W
1!
1-
#120000
b1100 M
b1100 `
b1100 u
b1100 !"
0!
0-
#140000
b111 <
b111 +
b111 @
b111 y
b1 O
b1 b
b1 x
bx F
bx w
bx ""
04
0&
05
0'
02
0$
17
1)
b10 9
b10 ,
b10 :
b1 |
b1 A
b1 v
b1 }
b1001 H
b1001 a
b1001 o
b10010000010101000 N
b10010000010101000 i
b10010000010101000 l
b10011 I
b10011 t
b10011 {
b101010 .
b101010 ;
b101010 D
b0 /
b0 1
b0 G
b1001 n
b10011 m
b100100000101010 g
b100100000101010 C
b100100000101010 f
b100100000101010 h
b100100000101010 s
b10011 ^
b10011 M
b10011 `
b10011 u
b10011 !"
b1000 ]
b1000 L
b1000 _
b1000 z
b10000 K
b10000 S
b10000 q
b1000100110100100000101010 E
b1000100110100100000101010 Z
b10010000010111000 ?
b10010000010111000 j
b10010000010111000 r
b10000 >
b10000 V
b10000 k
b10000 p
b1100 T
b1100 J
b1100 U
b1100 W
1!
1-
#160000
0!
0-
#180000
0B
0R
0e
0P
b11111111111111111111111111110101 |
b11111111111111111111111111110101 A
b11111111111111111111111111110101 v
b11111111111111111111111111110101 }
bx O
bx b
bx x
1Q
1d
b110 <
b110 +
b110 @
b110 y
x5
x'
b11 3
b11 %
b11 =
x7
x)
08
0*
b1 9
b1 ,
b1 :
b1xx1x H
b1xx1x a
b1xx1x o
b11111111111111111111111111111000 N
b11111111111111111111111111111000 i
b11111111111111111111111111111000 l
b1100 I
b1100 t
b1100 {
b111110 .
b111110 ;
b111110 D
b100 /
b100 1
b100 G
b11111 n
b10010 m
b1111111111111110 g
b11111111111111111111111111111110 C
b11111111111111111111111111111110 f
b11111111111111111111111111111110 h
b11111111111111111111111111111110 s
b10010 ^
b1100 M
b1100 `
b1100 u
b1100 !"
b1001 ]
b1 L
b1 _
b1 z
b10100 K
b10100 S
b10100 q
b10001001100101111111111111110 E
b10001001100101111111111111110 Z
b1100 ?
b1100 j
b1100 r
b10100 >
b10100 V
b10100 k
b10100 p
b10000 T
b10000 J
b10000 U
b10000 W
1!
1-
#200000
0!
0-
#220000
b1111 <
b1111 +
b1111 @
b1111 y
xB
xR
xe
xP
b11 9
b11 ,
b11 :
bx |
bx A
bx v
bx }
bx H
bx a
bx o
bx00 N
bx00 i
bx00 l
bx I
bx t
bx {
bx .
bx ;
bx D
bx /
bx 1
bx G
bx n
bx m
bx g
bx C
bx f
bx h
bx s
bx ^
bx M
bx `
bx u
bx !"
bx ]
bx L
bx _
bx z
bx K
bx S
bx q
bx E
bx Z
bx ?
bx j
bx r
b11000 >
b11000 V
b11000 k
b11000 p
b10100 T
b10100 J
b10100 U
b10100 W
1!
1-
#240000
0!
0-
#260000
bx >
bx V
bx k
bx p
bx T
bx J
bx U
bx W
1!
1-
