verilog lab8/library_input.v

`timescale 1ns/1ps


///////////////////////////////////////////////////////////////////////////////////
//~~~~~~~~~~~~~~~~~~~~~~~~~~~~~~~~~ ALU ~~~~~~~~~~~~~~~~~~~~~~~~~~~~~~~~~~~~~~~~~~//
//																				  //
// Small ALU. Inputs: inA, inB. Output: out. 									  //
// Operations: bitwise and (op = 0)												  //
//             bitwise or  (op = 1)												  //
//             addition (op = 2)												  //
//             subtraction (op = 6)												  //
//             slt  (op = 7)													  //
//             nor (op = 12)													  //
////////////////////////////////////////////////////////////////////////////////////

module ALU (out, zero, inA, inB, alu_ctrl);

  input [3:0] alu_ctrl;
  input [31:0] inA, inB;
  output reg [31:0] out;
  output wire zero;
  
  assign zero = out ? 0 : 1;
  
  always @ (alu_ctrl, inA, inB) begin
    
    case (alu_ctrl)
      4'b0000: out <= inA&inB;
      4'b0001: out <= inA | inB;       	// or
      4'b0010: out <= inA + inB;       	// add
      4'b0110: out <= inA - inB;       	// substract
      4'b0111: out <= inA < inB ? 1:0; 	// slt
      4'b1100: out <= ~(inA | inB);		// nor
      default: out <= 'bx;
    endcase
  end
  
endmodule

///////////////////////////////////////////////////////////////////////////////////
//~~~~~~~~~~~~~~~~~~~~~~~~~~~~~ Program Counter ~~~~~~~~~~~~~~~~~~~~~~~~~~~~~~~~//
//																				//
// 				Sets the new program counter as the current pc					//
//																				//
//////////////////////////////////////////////////////////////////////////////////

module ProgramCounter (clock, reset, PC_new, PC);

	input reset, clock;
	input [31:0] PC_new;
	output reg [31:0] PC;

	always @(posedge clock or negedge reset)
		begin
			if (reset == 1'b0)	// an to reset einai 0 krata 0 kai ton program counter
				PC <= 32'h0;
			else
				PC <= PC_new;	// alliws dwse ston trexon pc timh ish me thn epomenh dieu8unsh
		end

endmodule

///////////////////////////////////////////////////////////////////////////////////
//~~~~~~~~~~~~~~~~~~~~~~~~~~~~~~~~ Memory ~~~~~~~~~~~~~~~~~~~~~~~~~~~~~~~~~~~~~~//
//																				//
// 		Memory (active 1024 words, from 10 address lsbs).						//
//      Read : enable ren, address addr, data dout								//
//      Write: enable wen, address addr, data din.								//
//																				//
//////////////////////////////////////////////////////////////////////////////////

module Memory (clock, ren, wen, addr, din, dout);
  input		ren, wen, clock;
  input		[31:0] addr, din;
  output	[31:0] dout;

  reg [31:0] data[4095:0];
  wire [31:0] dout;

  always @(ren or wen)
    if (ren & wen)
      $display ("\nMemory ERROR (time %0d): ren and wen both active!\n", $time);

  always @(posedge ren or posedge wen) begin
    if (addr[31:10] != 0)
      $display("Memory WARNING (time %0d): address msbs are not zero\n", $time);
  end  

  assign dout = ((wen==1'b0) && (ren==1'b1)) ? data[addr[9:0]] : 32'bx;
  
  always @(negedge clock)
   begin
    if ((wen == 1'b1) && (ren==1'b0))
        data[addr[9:0]] = din;
   end

endmodule

///////////////////////////////////////////////////////////////////////////////////
//~~~~~~~~~~~~~~~~~~~~~~~~~~~~~~~Register File ~~~~~~~~~~~~~~~~~~~~~~~~~~~~~~~~~~//
//																				 //
// 		Read ports: address raA, data rdA										 //
//                          address raB, data rdB								 //
//      Write port: address wa, data wd, enable wen.							 //
//																				 //
///////////////////////////////////////////////////////////////////////////////////

module RegFile (clock, reset, raA, raB, wa, wen, wd, rdA, rdB);


	output wire [31:0] rdA, rdB;
	input [31:0] wd;
	input [4:0] raA, raB, wa;
	input wen, reset, clock;
	reg [31:0] data [31:0];
	integer i;


	assign rdA = data[raA];
	assign rdB = data[raB];
	// Write Section
	always @(negedge clock or negedge reset)	// the register file should be written at 
		begin								// the negative edge of the input clock

			if (reset==1'b0)
	  			for(i=0;i<32;i=i+1)
					data[i] <= i;		//otan to reset einai 0 mhdenizw olous ts kataxwrhtes
			else if (wen==1'b1)		// alliws dwse ston ka8e kataxwrhth timh idia me
				data[wa] <= wd;  	// idia me ton au3oda ari8mo tu
		end


endmodule

///////////////////////////////////////////////////////////////////////////////////
//~~~~~~~~~~~~~~~~~~~~~~~~~~~~~~~~ ADDER ~~~~~~~~~~~~~~~~~~~~~~~~~~~~~~~~~~~~~~~~~//
//																				  //
// 					Adds 4 bytes to move to the next instruction				  //
//																				  //
////////////////////////////////////////////////////////////////////////////////////

module Adder (current, next_pc);

	parameter step = 32'h4;
	input [31:0] current;
	output wire [31:0] next_pc;

	assign next_pc = current + step;
	
endmodule

////////////////////////////////////////////////////////////////////////////////////
//~~~~~~~~~~~~~~~~~~~~~~~~~~~~~~~~ ADDER2 ~~~~~~~~~~~~~~~~~~~~~~~~~~~~~~~~~~~~~~~~//
//																				  //
// 					Adds 4 bytes to shifted instruction							  //
//																				  //
////////////////////////////////////////////////////////////////////////////////////

module Adder2 (shifted_instr, next_pc, next_instr);

	input [31:0] shifted_instr, next_pc;
	output wire [31:0] next_instr;

	assign next_instr = shifted_instr + next_pc;
	
endmodule



///////////////////////////////////////////////////////////////////////////////////
//~~~~~~~~~~~~~~~~~~~~~~~~~~~~~~ SignExtend ~~~~~~~~~~~~~~~~~~~~~~~~~~~~~~~~~~~~~~//
//																				  //
// 					A module that extends the sign and adds zero				  //
//							   at the 2 LSB										  //
//																				  //
////////////////////////////////////////////////////////////////////////////////////

module SignExtend (instr, extended_instr);

	input[15:0] instr;
	output wire [31:0] extended_instr;
	
    assign extended_instr = {{16{instr[15]}}, instr[15:0]};

endmodule


///////////////////////////////////////////////////////////////////////////////////
//~~~~~~~~~~~~~~~~~~~~~~~~~~~~~~~~ Sifter ~~~~~~~~~~~~~~~~~~~~~~~~~~~~~~~~~~~~~~~~//
//																				  //
// 					A module that shifts left the LSB bits						  //
//																				  //
////////////////////////////////////////////////////////////////////////////////////

module Sifter (extended_instr, shifted_instr);

	input [31:0] extended_instr;
	output wire [31:0] shifted_instr;
	
	assign shifted_instr = extended_instr << 2;	
	
endmodule

////////////////////////////////////////////////////////////////////////////////////
//~~~~~~~~~~~~~~~~~~~~~~~~~~~~~~~~~ AND ~~~~~~~~~~~~~~~~~~~~~~~~~~~~~~~~~~~~~~~~~~//
//																				  //
// 							A simple 'and' gate									  //
//																				  //
////////////////////////////////////////////////////////////////////////////////////


module AND (zero, branch, select_signal);
	input zero, branch;
	output wire select_signal;
	
	assign select_signal = zero & branch;

endmodule


///////////////////////////////////////////////////////////////////////////////////
//~~~~~~~~~~~~~~~~~~~~~~~~~~~~ Multiplexers ~~~~~~~~~~~~~~~~~~~~~~~~~~~~~~~~~~~~~~//
//																				  //
// 					Four modules for each multiplexers in the circuit			  //
//																				  //
////////////////////////////////////////////////////////////////////////////////////


module MultiPlx_Ctrl_Reg (select, input1, input2, out);

	input [4:0] input1, input2;
	input select;
	output wire [4:0] out;
	
	assign out = (select==1'b1) ? input2 : input1;
	
endmodule


module MultiPlx_Add2_PC (select_signal, new_instr, next_pc, new_program_counter);

	input select_signal;
	input [31:0] new_instr, next_pc;
	output wire [31:0] new_program_counter;
	
	assign new_program_counter = (select_signal==1'b1) ? next_pc : new_instr;
	
endmodule


module MultiPlx_Reg_ALU (AluSrc, rdB, extended_instr, inB);

	input AluSrc;
	input [31:0] rdB, extended_instr;
	output wire [31:0] inB;
	
	assign inB = (AluSrc==1'b1) ? extended_instr : rdB;
	
endmodule


module MultiPlx_Mem_Reg (MemReg, dout, out, wd);
	
	input MemReg;
	input [31:0] dout, out;
	output wire [31:0] wd;
	
	assign wd = (MemReg==1'b1) ? out : dout;
	
endmodule

///////////////////////////////////////////////////////////////////////////////////
//~~~~~~~~~~~~~~~~~~~~~~~~~~~~~~~~~~ CPU ~~~~~~~~~~~~~~~~~~~~~~~~~~~~~~~~~~~~~~~~~//
//																				  //
// 					A module that describes the function of cpu					  //
//																				  //
////////////////////////////////////////////////////////////////////////////////////
                                                                                  
module CPU (clock, reset);

	input clock, reset;
	wire [1:0] alu_op;
	wire RegWrite, RegDist, AluSrc, Branch, MemWrite, MemReg, MemRead;
	wire [3:0] alu_ctrl;
	wire [5:0] op, func_code;
	
	// enwnoume to FSM me ta upoloipa stoixeia //
	Main_decoder	dec_main	(op, RegWrite, alu_op, RegDist, AluSrc, Branch, MemWrite, MemReg, MemRead);
	Alu_decoder		dec_alu		(alu_op, func_code, alu_ctrl);
	data_path		datapass 	(clock, reset, RegWrite, alu_ctrl, op, func_code, RegDist, AluSrc, Branch, MemWrite, MemReg, MemRead);

endmodule

verilog lab8/data_path.v

`timescale 1ns/1ps

module data_path (clock, reset, RegWrite, alu_ctrl, op, func_code, RegDist, AluSrc, Branch, MemWrite, MemReg, MemRead);

	input clock, reset;
	input RegWrite, RegDist, AluSrc, Branch, MemWrite, MemReg, MemRead;
	input [3:0] alu_ctrl;
	output [5:0] op, func_code;
	
	wire [31:0] instr, added_pc, pc_new, pc, rdA, rdB, din, wd, alu_out, adder2_out;
	wire [31:0] extended_instr, shifted_instr, mem_out, out_multi3;
	wire [4:0] out_multi1;
	wire and_out, zero;


	// enwnoume ola ta stoixeia //
	ProgramCounter	reloaded_pc	(clock, reset, pc_new, pc);
	Adder			additive	(pc, added_pc);
	
	Memory			mem_INSTR 	(clock, 1'b1, 1'b0, pc, 32'b0, instr);
	RegFile			cpu_regs	(clock, reset, instr[25:21], instr[20:16], out_multi1, RegWrite, wd, rdA, rdB);
	AND				and_gate	(zero, Branch, and_out);
	SignExtend		extended 	(instr[15:0], extended_instr);
	Sifter			sifted		(extended_instr, shifted_instr);
	Adder2			adder2 		(shifted_instr, added_pc, adder2_out);
	
	MultiPlx_Ctrl_Reg multi1 	(RegDist, instr[20:16], instr[15:11], out_multi1);
	MultiPlx_Add2_PC  multi2 	(and_out, added_pc, adder2_out, pc_new);
	MultiPlx_Reg_ALU  multi3 	(AluSrc, rdB, extended_instr, out_multi3);
	MultiPlx_Mem_Reg  multi4 	(MemReg, alu_out, mem_out, wd);
	
	ALU 			my_alu 		(alu_out, zero, rdA, out_multi3, alu_ctrl);
	Memory 			mem_DATA 	(clock, MemRead, MemWrite, alu_out, rdB, mem_out);
	
	assign op = instr[31:26];
	assign func_code = instr [5:0];

endmodule

verilog lab8/ctrl_unit.v
`include "constants.h"
`timescale 1ns/1ps

module Main_decoder (op, RegWrite, alu_op, RegDist, AluSrc, Branch, MemWrite, MemReg, MemRead);
	input [5:0] op;
	output reg [1:0] alu_op;
	output reg RegDist, RegWrite, AluSrc, Branch, MemWrite, MemReg, MemRead;

	always @(*)
		case (op)
			`R_FORMAT: 
				begin
					alu_op <= 2'b10;

					RegWrite <= 1'b1;
					RegDist <= 1'b1;
					AluSrc <= 1'b0;
					Branch <= 1'b0;
					MemWrite <= 1'b0;
					MemReg <= 1'b0;
					MemRead <= 1'b0;
				end
			`LW: 
				begin
					alu_op <= 2'b00;

					RegWrite <= 1'b1;
					RegDist <= 1'b0;
					AluSrc <= 1'b1;
					Branch <= 1'b0;
					MemWrite <= 1'b0;
					MemReg <= 1'b1;
					MemRead <= 1'b1;
				end
			`SW: 
				begin
					alu_op <= 2'b00;

					RegWrite <= 1'b0;
					RegDist <= 1'bx;
					AluSrc <= 1'b1;
					Branch <= 1'b0;
					MemWrite <= 1'b1;
					MemReg <= 1'bx;
					MemRead <= 1'b0;
				end
			`BEQ: 
				begin
					alu_op <= 2'b01;

					RegWrite <= 1'b0;
					RegDist <= 1'bx;
					AluSrc <= 1'b0;
					Branch <= 1'b1;
					MemWrite <= 1'b0; 
					MemReg <= 1'bx;
					MemRead <= 1'b0;
				end
			 default: alu_op <= 2'b11;  // ~NOP~ we should never reach this place
		endcase
endmodule

module Alu_decoder (alu_op, func_code, alu_ctrl);

	input [1:0] alu_op;
	input [5:0] func_code;
	output reg [3:0] alu_ctrl;

	always @(*)
		case (alu_op)
		2'b00: alu_ctrl <= 4'b0010; // lw, sw
		2'b01: alu_ctrl <= 4'b0110;	// branch
		2'b10:
			case (func_code)
				6'b100100: alu_ctrl <= 4'b0000;	// and
				6'b100101: alu_ctrl <= 4'b0001;	// or
				6'b100000: alu_ctrl <= 4'b0010;	// add
				6'b100010: alu_ctrl <= 4'b0110;	// substract
				6'b101010: alu_ctrl <= 4'b0111;	// slt
				6'b100111: alu_ctrl <= 4'b1100;	// nor
				default: alu_ctrl <= 4'b1111; 		// we should never reach this place!!!!!!!!!!!
			endcase
		default: alu_ctrl <= 4'b1111;
	endcase
endmodule

verilog lab8/testbench_input.v
// Define top-level testbench
// ~~~~~~~~~~~~~~~~~~~~~~~~~~~~~
// Top level has no inputs or outputs
// It only needs to instantiate CPU, Drive the inputs to CPU (clock, reset)
// and monitor the outputs. This is what all testbenches do

`include "constants.h"
`timescale 1ns/1ps
`define clock_period 10

module cpu_tb;
integer   i;
reg       clock, reset;    // Clock and reset signals

// Instantiate CPU here with name cpu0
CPU cpu0 (clock, reset); 

// Initialization and signal generation
// ~~~~~~~~~~~~~~~~~~~~~~~~~~~~~~~~

// Generate clock and reset signal here
 
  // Initialize Register File with initial values. 
  // cpu0 is the name of the cpu instance
  // cpu_regs is the name of the register file instance in the CPU verilog file 
  // data[] is the register file array 
initial begin 

	$dumpfile("lab8.vcd");
	$dumpvars(0, cpu_tb);
	clock = 1'b0;
	reset = 1'b0;
	 
	#(`clock_period*4) reset = 1'b1;


  // Initialize Data Memory. You have to develop "program.hex" as a text file 
  // which containsthe instruction opcodes as 32-bit hexadecimal values.
	for (i=0; i<4095; i=i+1)
		cpu0.datapass.mem_DATA.data[i]=32'b0;
	$readmemb("code2.mbin", cpu0.datapass.mem_INSTR.data);

  // Edw, to "program.hex" einai ena arxeio pou prepei na brisketai sto 
  // directory pou trexete th Verilog kai na einai ths morfhs:
  
  // @0    00000000
  // @4    20100009
  // @8    00000000
  // @C    00000000
  // ...
  
  // H aristerh sthlh, meta to @, exei th dieythynsh ths mnhmhs (hex),
  // kai h deksia sthlh ta dedomena sth dieythynsh ayth (pali hex).
  // Sto paradeigma pio panw, oi lekseis stis dieythynseis 0, 8 kai 12
  // einai 0, kai sth dieythynsh 4 exei thn timh 32'h20100009. An o PC
  // diabasei thn dieythynsh 4, h timh ekei exei thn entolh
  //   addi $16 <- $0 + 9

  // To deytero orisma ths $readmemh einai pou akribws brisketai h mnhmh
  // pou tha arxikopoihthei. Sto paradeigma, to "dat0" einai to onoma pou
  // dwsame sto instance tou datapath. To "mem" einai to onoma pou exei
  // to instance ths mnhmhs MESA sto datapath, kai to "data" einai to 
  // onoma pou exei to pragmatiko array ths mhnhs mesa sto module ths.
  // An exete dwsei diaforetika onomata, allakste thn $readmemh.

  // Enallaktika, an sas boleyei perissotero, yparxei h entolh $readmemb
  // me thn akribws idia syntaksh. H aristerh sthlh tou arxeiou exei
  // thn idia morfh (dieythynseis se hex), alla h deksia sthlh exei
  // ta dedomena sto dyadiko. Etsi h add mporouse na einai:

  // @4    00100000000100000000000000001001

  // ... h kai akoma kalytera:
  
  // @4    001000_00000_10000_0000000000001001

  // (h Verilog epitrepei diaxwristika underscores).

	
  // Termatismos ekteleshs:
	#(`clock_period * 40) $finish;

end  // initial 

always begin
	#(`clock_period/0.5) clock=~clock;
end
endmodule

verilog lab8/lab8.vcd
$date
	Sun Dec  8 14:32:38 2013
$end
$version
	Icarus Verilog
$end
$timescale
	1ps
$end
$scope module cpu_tb $end
$var reg 1 ! clock $end
$var integer 32 " i [31:0] $end
$var reg 1 # reset $end
$scope module cpu0 $end
$var wire 1 $ AluSrc $end
$var wire 1 % Branch $end
$var wire 1 & MemRead $end
$var wire 1 ' MemReg $end
$var wire 1 ( MemWrite $end
$var wire 1 ) RegDist $end
$var wire 1 * RegWrite $end
$var wire 4 + alu_ctrl [3:0] $end
$var wire 2 , alu_op [1:0] $end
$var wire 1 - clock $end
$var wire 6 . func_code [5:0] $end
$var wire 6 / op [5:0] $end
$var wire 1 0 reset $end
$scope module dec_main $end
$var wire 6 1 op [5:0] $end
$var reg 1 2 AluSrc $end
$var reg 1 3 Branch $end
$var reg 1 4 MemRead $end
$var reg 1 5 MemReg $end
$var reg 1 6 MemWrite $end
$var reg 1 7 RegDist $end
$var reg 1 8 RegWrite $end
$var reg 2 9 alu_op [1:0] $end
$upscope $end
$scope module dec_alu $end
$var wire 2 : alu_op [1:0] $end
$var wire 6 ; func_code [5:0] $end
$var reg 4 < alu_ctrl [3:0] $end
$upscope $end
$scope module datapass $end
$var wire 1 $ AluSrc $end
$var wire 1 % Branch $end
$var wire 1 & MemRead $end
$var wire 1 ' MemReg $end
$var wire 1 ( MemWrite $end
$var wire 1 ) RegDist $end
$var wire 1 * RegWrite $end
$var wire 32 = added_pc [31:0] $end
$var wire 32 > adder2_out [31:0] $end
$var wire 4 ? alu_ctrl [3:0] $end
$var wire 32 @ alu_out [31:0] $end
$var wire 1 A and_out $end
$var wire 1 - clock $end
$var wire 32 B extended_instr [31:0] $end
$var wire 6 C func_code [5:0] $end
$var wire 32 D instr [31:0] $end
$var wire 32 E mem_out [31:0] $end
$var wire 6 F op [5:0] $end
$var wire 5 G out_multi1 [4:0] $end
$var wire 32 H out_multi3 [31:0] $end
$var wire 32 I pc [31:0] $end
$var wire 32 J pc_new [31:0] $end
$var wire 32 K rdA [31:0] $end
$var wire 32 L rdB [31:0] $end
$var wire 1 0 reset $end
$var wire 32 M shifted_instr [31:0] $end
$var wire 32 N wd [31:0] $end
$var wire 1 O zero $end
$scope module reloaded_pc $end
$var wire 32 P PC_new [31:0] $end
$var wire 1 - clock $end
$var wire 1 0 reset $end
$var reg 32 Q PC [31:0] $end
$upscope $end
$scope module additive $end
$var wire 32 R current [31:0] $end
$var wire 32 S next_pc [31:0] $end
$upscope $end
$scope module mem_INSTR $end
$var wire 32 T addr [31:0] $end
$var wire 1 - clock $end
$var wire 32 U din [31:0] $end
$var wire 32 V dout [31:0] $end
$var wire 1 W ren $end
$var wire 1 X wen $end
$upscope $end
$scope module cpu_regs $end
$var wire 1 - clock $end
$var wire 5 Y raA [4:0] $end
$var wire 5 Z raB [4:0] $end
$var wire 32 [ rdA [31:0] $end
$var wire 32 \ rdB [31:0] $end
$var wire 1 0 reset $end
$var wire 5 ] wa [4:0] $end
$var wire 32 ^ wd [31:0] $end
$var wire 1 * wen $end
$var integer 32 _ i [31:0] $end
$upscope $end
$scope module and_gate $end
$var wire 1 % branch $end
$var wire 1 A select_signal $end
$var wire 1 O zero $end
$upscope $end
$scope module extended $end
$var wire 32 ` extended_instr [31:0] $end
$var wire 16 a instr [15:0] $end
$upscope $end
$scope module sifted $end
$var wire 32 b extended_instr [31:0] $end
$var wire 32 c shifted_instr [31:0] $end
$upscope $end
$scope module adder2 $end
$var wire 32 d next_instr [31:0] $end
$var wire 32 e next_pc [31:0] $end
$var wire 32 f shifted_instr [31:0] $end
$upscope $end
$scope module multi1 $end
$var wire 5 g input1 [4:0] $end
$var wire 5 h input2 [4:0] $end
$var wire 5 i out [4:0] $end
$var wire 1 ) select $end
$upscope $end
$scope module multi2 $end
$var wire 32 j new_instr [31:0] $end
$var wire 32 k new_program_counter [31:0] $end
$var wire 32 l next_pc [31:0] $end
$var wire 1 A select_signal $end
$upscope $end
$scope module multi3 $end
$var wire 1 $ AluSrc $end
$var wire 32 m extended_instr [31:0] $end
$var wire 32 n inB [31:0] $end
$var wire 32 o rdB [31:0] $end
$upscope $end
$scope module multi4 $end
$var wire 1 ' MemReg $end
$var wire 32 p dout [31:0] $end
$var wire 32 q out [31:0] $end
$var wire 32 r wd [31:0] $end
$upscope $end
$scope module my_alu $end
$var wire 4 s alu_ctrl [3:0] $end
$var wire 32 t inA [31:0] $end
$var wire 32 u inB [31:0] $end
$var wire 1 O zero $end
$var reg 32 v out [31:0] $end
$upscope $end
$scope module mem_DATA $end
$var wire 32 w addr [31:0] $end
$var wire 1 - clock $end
$var wire 32 x din [31:0] $end
$var wire 32 y dout [31:0] $end
$var wire 1 & ren $end
$var wire 1 ( wen $end
$upscope $end
$upscope $end
$upscope $end
$upscope $end
$enddefinitions $end
#0
$dumpvars
bx y
bx x
bx w
bx v
bx u
bx t
b1111 s
bx r
bx q
bx p
bx o
bx n
bx m
bx l
bx k
b100 j
bx i
bx h
bx g
bx00 f
b100 e
bx d
bx00 c
bx b
bx a
bx `
b100000 _
bx ^
bx ]
bx \
bx [
bx Z
bx Y
0X
1W
bx V
b0 U
b0 T
b100 S
b0 R
b0 Q
bx P
xO
bx N
bx00 M
bx L
bx K
bx J
b0 I
bx H
bx G
bx F
bx E
bx D
bx C
bx B
xA
bx @
b1111 ?
bx >
b100 =
b1111 <
bx ;
b11 :
b11 9
x8
x7
x6
x5
x4
x3
x2
bx 1
00
bx /
bx .
0-
b11 ,
b1111 +
x*
x)
x(
x'
x&
x%
x$
0#
bx "
0!
$end
#20000
1!
1-
#40000
0O
b10001 v
b10001 @
b10001 p
b10001 w
b10 <
b10 +
b10 ?
b10 s
0A
04
0&
16
1(
03
0%
12
1$
08
0*
b0 9
b0 ,
b0 :
b100 J
b100 P
b100 k
b10100 >
b10100 d
b10100 l
b0x000 G
b0x000 ]
b0x000 i
b10000 M
b10000 c
b10000 f
b100 H
b100 n
b100 u
b100 .
b100 ;
b100 C
b101011 /
b101011 1
b101011 F
b0 h
b1000 g
b100 a
b100 B
b100 `
b100 b
b100 m
b1000 Z
b1000 L
b1000 \
b1000 o
b1000 x
b1101 Y
b1101 K
b1101 [
b1101 t
b10101101101010000000000000000100 D
b10101101101010000000000000000100 V
0!
0-
b111111111111 "
1#
10
#60000
b0 N
b0 ^
b0 r
b0 E
b0 q
b0 y
14
1&
15
1'
06
0(
07
0)
18
1*
b1001 G
b1001 ]
b1001 i
b100011 /
b100011 1
b100011 F
b1001 g
b1001 Z
b1001 L
b1001 \
b1001 o
b1001 x
b1000 J
b1000 P
b1000 k
b10001101101010010000000000000100 D
b10001101101010010000000000000100 V
b11000 >
b11000 d
b11000 l
b1000 =
b1000 S
b1000 e
b1000 j
b100 Q
b100 I
b100 R
b100 T
1!
1-
#80000
b0 L
b0 \
b0 o
b0 x
0!
0-
#100000
b1111 <
b1111 +
b1111 ?
b1111 s
bx N
bx ^
bx r
bx E
bx q
bx y
xO
b11 9
b11 ,
b11 :
bx v
bx @
bx p
bx w
bx G
bx ]
bx i
bx00 M
bx00 c
bx00 f
bx H
bx n
bx u
bx .
bx ;
bx C
bx /
bx 1
bx F
bx h
bx g
bx a
bx B
bx `
bx b
bx m
bx Z
bx L
bx \
bx o
bx x
bx Y
bx K
bx [
bx t
b1100 J
b1100 P
b1100 k
bx D
bx V
bx >
bx d
bx l
b1100 =
b1100 S
b1100 e
b1100 j
b1000 Q
b1000 I
b1000 R
b1000 T
1!
1-
#120000
0!
0-
#140000
b10000 J
b10000 P
b10000 k
b10000 =
b10000 S
b10000 e
b10000 j
b1100 Q
b1100 I
b1100 R
b1100 T
1!
1-
#160000
0!
0-
#180000
b10100 J
b10100 P
b10100 k
b10100 =
b10100 S
b10100 e
b10100 j
b10000 Q
b10000 I
b10000 R
b10000 T
1!
1-
#200000
0!
0-
#220000
b11000 J
b11000 P
b11000 k
b11000 =
b11000 S
b11000 e
b11000 j
b10100 Q
b10100 I
b10100 R
b10100 T
1!
1-
#240000
0!
0-
#260000
b11100 J
b11100 P
b11100 k
b11100 =
b11100 S
b11100 e
b11100 j
b11000 Q
b11000 I
b11000 R
b11000 T
1!
1-
#280000
0!
0-
#300000
b100000 J
b100000 P
b100000 k
b100000 =
b100000 S
b100000 e
b100000 j
b11100 Q
b11100 I
b11100 R
b11100 T
1!
1-
#320000
0!
0-
#340000
b100100 J
b100100 P
b100100 k
b100100 =
b100100 S
b100100 e
b100100 j
b100000 Q
b100000 I
b100000 R
b100000 T
1!
1-
#360000
0!
0-
#380000
b101000 J
b101000 P
b101000 k
b101000 =
b101000 S
b101000 e
b101000 j
b100100 Q
b100100 I
b100100 R
b100100 T
1!
1-
#400000
0!
0-
#420000
b101100 J
b101100 P
b101100 k
b101100 =
b101100 S
b101100 e
b101100 j
b101000 Q
b101000 I
b101000 R
b101000 T
1!
1-
